timed_rotating_text_file/__init__.py
timed_rotating_text_file/test.py
timed_rotating_text_file-0.0.7.dist-info/LICENSE
timed_rotating_text_file-0.0.7.dist-info/METADATA
timed_rotating_text_file-0.0.7.dist-info/WHEEL
timed_rotating_text_file-0.0.7.dist-info/top_level.txt
timed_rotating_text_file-0.0.7.dist-info/RECORD
