Metadata-Version: 2.1
Name: timed-rotating-text-file
Version: 0.0.7
Summary: A ZERO dependency rotating text file handler which rotates when YOU want it to, like TimedRotatingFileHandler provided by Python's logging module.
Home-page: https://github.com/bahamut45/timed-rotating-text-file
Author: bahamut45
Author-email: njoubert45@gmail.com
License: UNKNOWN
Keywords: custom rotating file handler textfile logger
Platform: UNKNOWN
Classifier: Development Status :: 5 - Production/Stable
Classifier: Environment :: Console
Classifier: Natural Language :: English
Classifier: License :: OSI Approved :: GNU General Public License v3 (GPLv3)
Classifier: Operating System :: OS Independent
Classifier: Programming Language :: Python
Classifier: Programming Language :: Python :: 2
Classifier: Programming Language :: Python :: 3
Classifier: Intended Audience :: Developers
License-File: LICENSE
